msc/__init__.py
msc/mumu.py
msc_mumu-0.0.2.dist-info/METADATA
msc_mumu-0.0.2.dist-info/WHEEL
msc_mumu-0.0.2.dist-info/top_level.txt
msc_mumu-0.0.2.dist-info/RECORD
