Metadata-Version: 2.1
Name: msc-mumu
Version: 0.0.2
Summary: 截图工具-mumu
Author: KateTseng
Author-email: Kate.TsengK@outlook.com
License: MIT
Keywords: Auto Script Testing
Requires-Python: >=3
Requires-Dist: opencv-python
Requires-Dist: adbutils
Requires-Dist: loguru
Requires-Dist: mmumu
Requires-Dist: msc-base
